{
	"credit": "Made with Blockbench",
	"parent": "javelin",
	"texture_size": [24, 48],
	"textures": {
		"0": "simplyswords:custom/iron_spear",
		"particle": "simplyswords:custom/iron_spear"
	},
	"elements": [
		{
			"from": [6.5, 16, 6.5],
			"to": [9.5, 18, 9.5],
			"faces": {
				"north": {"uv": [10, 1, 12, 1.66667], "texture": "#0"},
				"east": {"uv": [8, 1, 10, 1.66667], "texture": "#0"},
				"south": {"uv": [14, 1, 16, 1.66667], "texture": "#0"},
				"west": {"uv": [12, 1, 14, 1.66667], "texture": "#0"},
				"up": {"uv": [12, 1, 10, 0], "texture": "#0"},
				"down": {"uv": [14, 0, 12, 1], "texture": "#0"}
			}
		},
		{
			"from": [7, 18, 7],
			"to": [9, 20, 9],
			"faces": {
				"north": {"uv": [12, 3, 13.33333, 3.66667], "texture": "#0"},
				"east": {"uv": [10.66667, 3, 12, 3.66667], "texture": "#0"},
				"south": {"uv": [14.66667, 3, 16, 3.66667], "texture": "#0"},
				"west": {"uv": [13.33333, 3, 14.66667, 3.66667], "texture": "#0"},
				"up": {"uv": [13.33333, 3, 12, 2.33333], "texture": "#0"},
				"down": {"uv": [14.66667, 2.33333, 13.33333, 3], "texture": "#0"}
			}
		},
		{
			"from": [8, 18, 5.5],
			"to": [8, 27, 10.5],
			"rotation": {"angle": -45, "axis": "y", "origin": [8, 22.5, 8]},
			"faces": {
				"north": {"uv": [3.33333, 13, 3.33333, 16], "texture": "#0"},
				"east": {"uv": [0, 13, 3.33333, 16], "texture": "#0"},
				"south": {"uv": [6.66667, 13, 6.66667, 16], "texture": "#0"},
				"west": {"uv": [3.33333, 13, 6.66667, 16], "texture": "#0"},
				"up": {"uv": [3.33333, 13, 3.33333, 11.33333], "texture": "#0"},
				"down": {"uv": [3.33333, 11.33333, 3.33333, 13], "texture": "#0"}
			}
		},
		{
			"from": [8, 18, 5.5],
			"to": [8, 27, 10.5],
			"rotation": {"angle": 45, "axis": "y", "origin": [8, 22.5, 8]},
			"faces": {
				"north": {"uv": [3.33333, 13, 3.33333, 16], "texture": "#0"},
				"east": {"uv": [0, 13, 3.33333, 16], "texture": "#0"},
				"south": {"uv": [6.66667, 13, 6.66667, 16], "texture": "#0"},
				"west": {"uv": [3.33333, 13, 6.66667, 16], "texture": "#0"},
				"up": {"uv": [3.33333, 13, 3.33333, 11.33333], "texture": "#0"},
				"down": {"uv": [3.33333, 11.33333, 3.33333, 13], "texture": "#0"}
			}
		}
	],
	"display": {
		"thirdperson_righthand": {
			"translation": [0, -9.5, 0]
		},
		"thirdperson_lefthand": {
			"translation": [0, -8.5, 0]
		},
		"firstperson_righthand": {
			"rotation": [2.25, 15, -5],
			"translation": [0, -9.25, 0]
		},
		"firstperson_lefthand": {
			"rotation": [5.5, 19, -5],
			"translation": [1, -8.5, -0.25]
		},
		"ground": {
			"rotation": [72.96, -28.24, -24.67],
			"translation": [-4.75, -3.5, -10.75]
		},
		"gui": {
			"rotation": [25, 25, 0],
			"translation": [0, -17.75, 0],
			"scale": [1.5, 1.5, 1.5]
		},
		"fixed": {
			"rotation": [0, -90, 0],
			"translation": [0, -21.25, -1.5],
			"scale": [1.6, 1.6, 1.6]
		}
	}
}